{
  "generated_at": "2026-06-16T08:35:47+00:00",
  "source_url": "https://activesg.gov.sg/gym-pool-crowd",
  "reading": {
    "scraped_at": "2026-06-16T08:35:46+00:00",
    "source_updated_at": "2026-06-16T16:35:00+08:00",
    "facility": "Clementi ActiveSG Gym",
    "status": "open",
    "capacity_percentage": "47",
    "badge_text": "47% full",
    "raw_text": "{\"id\":\"EcBGtBDRSadwhso2WV0Tk\",\"name\":\"Clementi ActiveSG Gym\",\"capacityPercentage\":47,\"type\":\"gym\",\"isClosed\":false}",
    "source": "api_response"
  }
}
